{
	"intro": {
		"name": "Maythawat Mahawan",
		"nickname": "Tawan",
		"phone": "",
		"email": "tawan.csmju@gmail.com",
		"github": "moking55",
		"linkedin": "maythawat-mahawan",
		"location": "Chiang Mai, Thailand",
		"website": "codename-t.com"
	},
	"projects": [
		{
			"name": "Dormitory Plus!",
			"details": "A Dormitory management system for organizing and managing dormitories efficiently.",
			"url": "",
			"hide": false
		},
		{
			"name": "ComCamp 22",
			"details": "An official website for ComCamp 22, an annual computer camp held at Maejo University.",
			"url": "http://comcamp.csmju.com",
			"hide": false
		},
		{
			"name": "BCITSVC",
			"details": "A modern faculty website for an educational institution, designed for user-friendly information and resources.",
			"url": "http://bcitsvc.com",
			"hide": false
		},
		{
			"name": "VTuber.in.th",
			"details": "A Thai VTuber tracking website providing information and updates on popular virtual YouTubers.",
			"url": "http://vtuber.in.th",
			"hide": false
		},
		{
			"name": "MC Mart",
			"details": "A standalone Minecraft webshop developed using the CodeIgniter 4 framework.",
			"url": "https://github.com/moking55/mc-mart",
			"hide": false
		},
		{
			"name": "Liquiix Webshop",
			"details": "A custom Minecraft webshop tailored for the 'Liquiix RPG Server'.",
			"url": "https://github.com/moking55/liquiix-webshop",
			"hide": false
		},
		{
			"name": "ClassX",
			"details": "An efficient online classroom platform for seamless virtual learning experiences.",
			"url": "https://github.com/moking55/ClassX-simple-classroom",
			"hide": false
		},
		{
			"name": "LTC Guide",
			"details": "A handy student handbook application created using the Flutter framework.",
			"url": "http://thaiinvention.net",
			"hide": false
		}
	],
	"technologies": [
		{
			"section": "Languages:",
			"details": "Node.js, JavaScript, TypeScript, SQL, Python, PHP"
		},
		{
			"section": "Frameworks:",
			"details": "CodeIgniter 4, Express, NestJS, Vue.js, Vuetify, Tailwind CSS, Bootstrap, Nuxt 3, Next.js"
		},
		{
			"section": "Databases:",
			"details": "Firebase (Firestore & Authentication), MySQL, PostgreSQL, Redis"
		},
		{
			"section": "Tools:",
			"details": "Jenkins, Portainer, Docker, Nginx, Termius"
		},
		{
			"section": "Others:",
			"details": "Vercel, Cloudflare, GitHub, GitHub Actions, GitLab, Notion"
		}
	],
	"workExperiences": [
		{
			"position": "(Research & Development) Full-stack Developer",
			"company": "Dudee Indeed Co., Ltd.",
			"url": "https://dudee-indeed.com",
			"years": ["2024", "Present"],
			"details": [
				"Developed and maintained the company's website and internal systems.",
				"Created a POS system for the restaurant business.",
				"Researched and implemented new technologies to improve the company's workflow."
			]
		},
		{
			"position": "Internship Back-end Developer",
			"company": "Dudee Indeed Co., Ltd.",
			"url": "https://dudee-indeed.com",
			"years": ["2024 (6 months)"],
			"details": [
				"Developed and maintained back-end services for the company's projects.",
				"Collaborated with the front-end team to ensure seamless integration of services."
			]
		}
	],
	"educations": [
		{
			"head": "Bachelor's Degree in Computer Science",
			"details": "Maejo University, Thailand (2021 - Present) GPA: 3.45"
		}
	],
	"interests": [
		"Areas : Coding, Productivity & Life-hacks",
		"Languages : Thai, English",
		"Interests : Web Development, Software Engineering, Cloud Computing, Virtual YouTubers"
	],
	"resumeUrl": {
		"sourceLink": "https://github.com/moking55/resume-v2",
		"fullVersion": "https://resume.codename-t.com"
	}
}
